certbot_dns_sakuracloud/__init__.py
certbot_dns_sakuracloud/py.typed
certbot_dns_sakuracloud/_internal/__init__.py
certbot_dns_sakuracloud/_internal/dns_sakuracloud.py
certbot_dns_sakuracloud/_internal/tests/__init__.py
certbot_dns_sakuracloud/_internal/tests/dns_sakuracloud_test.py
certbot_dns_sakuracloud-5.1.0.dist-info/licenses/LICENSE.txt
certbot_dns_sakuracloud-5.1.0.dist-info/METADATA
certbot_dns_sakuracloud-5.1.0.dist-info/WHEEL
certbot_dns_sakuracloud-5.1.0.dist-info/entry_points.txt
certbot_dns_sakuracloud-5.1.0.dist-info/top_level.txt
certbot_dns_sakuracloud-5.1.0.dist-info/RECORD
