Metadata-Version: 2.4
Name: certbot-dns-sakuracloud
Version: 5.1.0
Summary: Sakura Cloud DNS Authenticator plugin for Certbot
Author-email: Certbot Project <certbot-dev@eff.org>
License-Expression: Apache-2.0
Project-URL: Homepage, https://github.com/certbot/certbot
Classifier: Development Status :: 5 - Production/Stable
Classifier: Environment :: Plugins
Classifier: Intended Audience :: System Administrators
Classifier: Operating System :: POSIX :: Linux
Classifier: Programming Language :: Python
Classifier: Programming Language :: Python :: 3
Classifier: Programming Language :: Python :: 3.13
Classifier: Programming Language :: Python :: 3.10
Classifier: Programming Language :: Python :: 3.11
Classifier: Programming Language :: Python :: 3.12
Classifier: Topic :: Internet :: WWW/HTTP
Classifier: Topic :: Security
Classifier: Topic :: System :: Installation/Setup
Classifier: Topic :: System :: Networking
Classifier: Topic :: System :: Systems Administration
Classifier: Topic :: Utilities
Requires-Python: >=3.10
License-File: LICENSE.txt
Requires-Dist: dns-lexicon>=3.14.1
Requires-Dist: acme>=5.1.0
Requires-Dist: certbot>=5.1.0
Provides-Extra: docs
Requires-Dist: Sphinx>=1.0; extra == "docs"
Requires-Dist: sphinx_rtd_theme; extra == "docs"
Provides-Extra: test
Requires-Dist: pytest; extra == "test"
Dynamic: license-file
Dynamic: requires-dist
